CHANGELOG
LICENSE
MANIFEST.in
README.rst
setup.py
patterns/__init__.py
patterns/cross.py
patterns/helpers.py
patterns/transform.py
patterns.egg-info/PKG-INFO
patterns.egg-info/SOURCES.txt
patterns.egg-info/dependency_links.txt
patterns.egg-info/requires.txt
patterns.egg-info/top_level.txt